simunetcore/__init__.py
simunetcore/aws.py
simunetcore/exception.py
simunetcore/factory.py
simunetcore/invoker.py
simunetcore/logger.py
simunetcore/model.py
simunetcore/mqtt.py
simunetcore/plot.py
simunetcore/rest.py
simunetcore/serializer.py
simunetcore/utils.py
simunetcore/waveform.py
simunetcore-0.0.22.dist-info/LICENSE
simunetcore-0.0.22.dist-info/METADATA
simunetcore-0.0.22.dist-info/WHEEL
simunetcore-0.0.22.dist-info/top_level.txt
simunetcore-0.0.22.dist-info/RECORD
