Metadata-Version: 2.1
Name: simunetcore
Version: 0.0.22
Summary: Co simulation package
Author-email: Thorsten Wack <thorsten.wack@umsicht.fraunhofer.de>
Project-URL: Homepage, https://simunet.org
Classifier: Programming Language :: Python :: 3
Classifier: License :: OSI Approved :: MIT License
Classifier: Operating System :: OS Independent
Requires-Python: >=3.7
License-File: LICENSE
Requires-Dist: boto3
Requires-Dist: botocore
Requires-Dist: jsonschema
Requires-Dist: matplotlib
Requires-Dist: networkx
Requires-Dist: numpy
Requires-Dist: paho-mqtt
Requires-Dist: Pint
Requires-Dist: requests
